README
setup.py
simple_import.py
simple_import.egg-info/PKG-INFO
simple_import.egg-info/SOURCES.txt
simple_import.egg-info/dependency_links.txt
simple_import.egg-info/top_level.txt