Metadata-Version: 1.0
Name: simple-import
Version: 0.1.1
Summary: UNKNOWN
Home-page: UNKNOWN
Author: Gabriel Grant
Author-email: g@briel.ca
License: LGPL
Platform: UNKNOWN
